tropokta/__init__.py
tropokta/okta.py
tropokta-0.0.3.dist-info/LICENSE
tropokta-0.0.3.dist-info/METADATA
tropokta-0.0.3.dist-info/WHEEL
tropokta-0.0.3.dist-info/top_level.txt
tropokta-0.0.3.dist-info/RECORD
