Metadata-Version: 2.1
Name: tropokta
Version: 0.0.3
Summary: Custom Okta Resources for AWS Cloudformation
Home-page: https://github.com/thebenwaters/tropokta
Author: Ben Waters
Author-email: bsawyerwaters@gmail.com
License: MIT
Keywords: okta cf cloudformation
Platform: UNKNOWN
Classifier: Development Status :: 3 - Alpha
Classifier: License :: OSI Approved :: MIT License
Classifier: Programming Language :: Python :: 2
Classifier: Programming Language :: Python :: 3
Requires-Dist: troposphere
